adventkit/__init__.py
adventkit/_version.py
adventkit/grids.py
adventkit/helpers.py
adventkit/parse.py
adventkit/solve.py
adventkit/year2017/__init__.py
adventkit/year2017/day01_inverse_captcha.py
adventkit/year2017/day02_corruption_checksum.py
adventkit/year2017/day03_spiral_memory.py
adventkit/year2017/day04_passphrases.py
adventkit/year2019/__init__.py
adventkit/year2019/day01_rocket_equation.py
adventkit/year2019/day02_1202_program_alarm.py
adventkit/year2019/day03_crossed_wires.py
adventkit/year2019/day04_secure_container.py
adventkit/year2019/day05_chance_of_asteroids.py
adventkit/year2019/day06_universal_orbit_map.py
adventkit/year2019/day07_amplification_circuit.py
adventkit/year2019/day08_space_image_format.py
adventkit/year2019/day09_sensor_boost.py
adventkit/year2019/day10_monitoring_station.py
adventkit/year2019/day11_space_police.py
adventkit/year2020/__init__.py
adventkit/year2020/day01_report_repair.py
adventkit/year2020/day02_password_philosophy.py
adventkit/year2020/day03_toboggan_trajectory.py
adventkit/year2020/day04_passport_processing.py
adventkit/year2020/day05_binary_boarding.py
adventkit/year2020/day06_custom_customs.py
adventkit/year2020/day07_handy_haversacks.py
adventkit/year2020/day08_handheld_halting.py
adventkit/year2020/day09_encoding_error.py
adventkit/year2020/day10_adapter_array.py
adventkit/year2020/day11_seating_system.py
adventkit/year2020/day12_rain_risk.py
adventkit-0.2.0.dist-info/entry_points.txt
adventkit-0.2.0.dist-info/LICENSE.txt
adventkit-0.2.0.dist-info/WHEEL
adventkit-0.2.0.dist-info/METADATA
adventkit-0.2.0.dist-info/RECORD
