Metadata-Version: 2.1
Name: adventkit
Version: 0.2.0
Summary: Solutions to Advent of Code puzzles.
Keywords: Advent of Code,puzzles
Author-email: Lukas Gelbmann <me@lukasgelbmann.com>
Maintainer-email: Lukas Gelbmann <me@lukasgelbmann.com>
Requires-Python: >= 3.6.1
Classifier: Development Status :: 4 - Beta
Classifier: Environment :: Console
Classifier: Intended Audience :: Developers
Classifier: License :: OSI Approved :: MIT License
Classifier: Natural Language :: English
Classifier: Operating System :: OS Independent
Classifier: Programming Language :: Python :: 3
Classifier: Topic :: Games/Entertainment :: Puzzle Games
Project-URL: Source, https://github.com/LukasGelbmann/adventkit
